{
  "$schema": "http://json-schema.org/draft-04/schema#",
  "title": "WindPatternConfig[]",
  "type": "array",
  "items": {
    "$ref": "#/definitions/WindPatternConfig"
  },
  "definitions": {
    "WindPatternConfig": {
      "type": "object",
      "properties": {
        "code": {
          "type": "string"
        },
        "durationHours": {
          "$ref": "../../lib/definitions/NatFloat.json#"
        },
        "name": {
          "type": "string"
        },
        "strength": {
          "$ref": "../../lib/definitions/NatFloat.json#"
        },
        "strengthNoise": {
          "$ref": "../../lib/definitions/NoiseConfig.json#"
        },
        "weight": {
          "type": "number",
          "format": "float"
        }
      }
    }
  }
}